timbl.py
timblapi.cpython-313-darwin.so
python3_timbl-2025.5.2.dist-info/RECORD
python3_timbl-2025.5.2.dist-info/WHEEL
python3_timbl-2025.5.2.dist-info/top_level.txt
python3_timbl-2025.5.2.dist-info/METADATA
python3_timbl-2025.5.2.dist-info/licenses/COPYING
python3_timbl.dylibs/libboost_python313.dylib
python3_timbl.dylibs/libxml2.2.dylib
python3_timbl.dylibs/libticcutils.10.dylib
python3_timbl.dylibs/libicudata.77.1.dylib
python3_timbl.dylibs/libicuuc.77.1.dylib
python3_timbl.dylibs/libz.1.3.1.dylib
python3_timbl.dylibs/libicuio.77.1.dylib
python3_timbl.dylibs/libtimbl.7.dylib
python3_timbl.dylibs/libicui18n.77.1.dylib
