Metadata-Version: 2.4
Name: python3-timbl
Version: 2025.5.2
Summary: Python 3 language binding for the Tilburg Memory-Based Learner
Home-page: http://github.com/proycon/python-timbl
Author: Sander Canisius, Maarten van Gompel
Author-email: S.V.M.Canisius@uvt.nl, proycon@anaproy.nl
License: GPL
Classifier: Development Status :: 4 - Beta
Classifier: Topic :: Text Processing :: Linguistic
Classifier: Topic :: Scientific/Engineering
Classifier: Programming Language :: Python :: 3
Classifier: Operating System :: POSIX
Classifier: Intended Audience :: Developers
Classifier: Intended Audience :: Science/Research
Classifier: License :: OSI Approved :: GNU General Public License v3 (GPLv3)
License-File: COPYING
Dynamic: author
Dynamic: author-email
Dynamic: classifier
Dynamic: home-page
Dynamic: license
Dynamic: license-file
Dynamic: summary
